elastic_models_cli/__init__.py
elastic_models_cli/entry.py
elastic_models_cli/logger.py
elastic_models_cli/cli/__init__.py
elastic_models_cli/cli/base.py
elastic_models_cli/cli/benchmark.py
elastic_models_cli/cli/client.py
elastic_models_cli/cli/registry.py
elastic_models_cli/cli/utils.py
elastic_models_cli/client/__init__.py
elastic_models_cli/client/diffusion/__init__.py
elastic_models_cli/client/diffusion/client.py
elastic_models_cli/client/diffusion/locustfile.py
elastic_models_cli/client/llm/__init__.py
elastic_models_cli/client/llm/client.py
elastic_models_cli/client/llm/locustfile.py
elastic_models_cli/client/stt/__init__.py
elastic_models_cli/client/stt/client.py
elastic_models_cli/client/stt/locustfile.py
elastic_models_cli/client/vlm/__init__.py
elastic_models_cli/client/vlm/client.py
thestage_elastic_models_cli-0.0.18.dist-info/licenses/LICENSE
thestage_elastic_models_cli-0.0.18.dist-info/METADATA
thestage_elastic_models_cli-0.0.18.dist-info/WHEEL
thestage_elastic_models_cli-0.0.18.dist-info/entry_points.txt
thestage_elastic_models_cli-0.0.18.dist-info/top_level.txt
thestage_elastic_models_cli-0.0.18.dist-info/RECORD
