Metadata-Version: 2.4
Name: thestage-elastic-models-cli
Version: 0.0.18
Summary: Elastic Models Client from TheStage AI
Author-email: TheStage AI team <hello@thestage.ai>
Classifier: Programming Language :: Python :: 3.10
Classifier: Programming Language :: Python :: 3.11
Classifier: Programming Language :: Python :: 3.12
Requires-Python: >=3.10
License-File: LICENSE
Requires-Dist: qlip_serve_client==0.1.17
Requires-Dist: locust
Requires-Dist: locust-plugins
Requires-Dist: Pillow
Requires-Dist: requests
Requires-Dist: wheel
Requires-Dist: numpy<2,>=1.23.5
Requires-Dist: aiohttp
Dynamic: license-file
